cygnus/__init__.py
cygnus-0.0.1.dist-info/LICENSE
cygnus-0.0.1.dist-info/METADATA
cygnus-0.0.1.dist-info/WHEEL
cygnus-0.0.1.dist-info/top_level.txt
cygnus-0.0.1.dist-info/RECORD
