Metadata-Version: 2.1
Name: cygnus
Version: 0.0.1
Summary: An Intelligent Agents Framework
Home-page: https://github.com/ysenarath/cygnus
Author: Yasas Senarath
Author-email: ysenarath.93@gmail.com
License: UNKNOWN
Platform: UNKNOWN
Classifier: Programming Language :: Python :: 3
Classifier: License :: OSI Approved :: MIT License
Classifier: Operating System :: OS Independent
Requires-Python: >=3.6
